collection_fc/__init__.py
collection_fc/__main__.py
collection_fc/bucket.py
collection_fc/cli.py
collection_fc/flexible.py
collection_fc/simple.py
collection_fc-0.1.0.dist-info/licenses/LICENSE
collection_fc-0.1.0.dist-info/METADATA
collection_fc-0.1.0.dist-info/WHEEL
collection_fc-0.1.0.dist-info/top_level.txt
collection_fc-0.1.0.dist-info/RECORD
