Metadata-Version: 2.4
Name: collection-fc
Version: 0.1.0
Summary: A flexible, easy-to-use Python library for collection forecasting.
Author: Monish Gosar
Author-email: Monish Gosar <your.email@example.com>
License: MIT License
Keywords: collections,forecasting,finance,transition matrix,cashflow
Classifier: Programming Language :: Python :: 3
Classifier: License :: OSI Approved :: MIT License
Classifier: Operating System :: OS Independent
Requires-Python: >=3.7
License-File: LICENSE
Requires-Dist: pandas
Requires-Dist: numpy
Dynamic: author
Dynamic: license-file
